kinesis_logger_streamhandler/__init__.py
kinesis_logger_streamhandler/kinesis_logger_stream_handler.py
kinesis_logger_streamhandler-0.0.8.dist-info/LICENSE
kinesis_logger_streamhandler-0.0.8.dist-info/METADATA
kinesis_logger_streamhandler-0.0.8.dist-info/WHEEL
kinesis_logger_streamhandler-0.0.8.dist-info/top_level.txt
kinesis_logger_streamhandler-0.0.8.dist-info/RECORD
