Metadata-Version: 2.1
Name: kinesis-logger-streamhandler
Version: 0.0.8
Summary: AWS Kinesis logger streamhandler with AWS Session Management
Home-page: https://github.com/deromka/kinesis-logger-streamhandler
Author: Roman Dembitsky
Author-email: romande@gmail.com
License: UNKNOWN
Platform: UNKNOWN
Classifier: Programming Language :: Python :: 3
Classifier: License :: OSI Approved :: MIT License
Classifier: Operating System :: OS Independent
Requires-Python: >=3.7
License-File: LICENSE
